Oscillo/Agilent.py
Oscillo/Agilent_DSO.py
Oscillo/Keyseight.py
Oscillo/Keyseight_DSOX.py
Oscillo/Oscillo.py
Oscillo/Tektronix.py
Oscillo/Tektronix_TBS.py
Oscillo/Tektronix_TDS.py
Oscillo/__init__.py
tpp7-2024.9.17.data/scripts/minimalTPUsage.py
tpp7-2024.9.17.dist-info/.ipynb_checkpoints/PKG-INFO-checkpoint
tpp7-2024.9.17.dist-info/.ipynb_checkpoints/SOURCES-checkpoint.txt
tpp7-2024.9.17.dist-info/.ipynb_checkpoints/dependency_links-checkpoint.txt
tpp7-2024.9.17.dist-info/.ipynb_checkpoints/top_level-checkpoint.txt
tpp7-2024.9.17.dist-info/LICENSE
tpp7-2024.9.17.dist-info/METADATA
tpp7-2024.9.17.dist-info/WHEEL
tpp7-2024.9.17.dist-info/top_level.txt
tpp7-2024.9.17.dist-info/RECORD
