Metadata-Version: 2.1
Name: tpp7
Version: 2024.9.17
Summary: Un paquetage pour les TP de Physique d'Université Paris-Cité
Home-page: https://github.com/cardosoo/tp
Author: Olivier Cardoso
Author-email: Olivier.Cardoso@univ-paris-diderot.fr
Classifier: Programming Language :: Python :: 3
Classifier: License :: OSI Approved :: MIT License
Classifier: Operating System :: OS Independent
Requires-Python: >=3.6
License-File: LICENSE
Requires-Dist: numpy
Requires-Dist: scipy
Requires-Dist: matplotlib
Requires-Dist: python-usbtmc
Requires-Dist: pandas
Requires-Dist: pyusb
Requires-Dist: fitutils
